django_fs_email_helper-0.3.dist-info/DESCRIPTION.rst
django_fs_email_helper-0.3.dist-info/METADATA
django_fs_email_helper-0.3.dist-info/RECORD
django_fs_email_helper-0.3.dist-info/WHEEL
django_fs_email_helper-0.3.dist-info/metadata.json
django_fs_email_helper-0.3.dist-info/top_level.txt
email_helper/__init__.py
email_helper/admin.py
email_helper/models.py
email_helper/locale/ru/LC_MESSAGES/django.mo
email_helper/locale/ru/LC_MESSAGES/django.po
email_helper/migrations/0001_initial.py
email_helper/migrations/__init__.py
