Metadata-Version: 2.0
Name: django-fs-email-helper
Version: 0.3
Summary: The Django-related reusable app provides the ability to send multipart emails and store them in a database.
Home-page: https://bitbucket.org/fogstream/django-fs-email-helper
Author: Yuri Lya
Author-email: yuri.lya@fogstream.ru
License: The MIT License (MIT)
Platform: UNKNOWN
Classifier: Development Status :: 5 - Production/Stable
Classifier: Environment :: Web Environment
Classifier: Intended Audience :: Developers
Classifier: Operating System :: OS Independent
Classifier: Programming Language :: Python
Classifier: Framework :: Django
Requires-Dist: html2text
